Metadata-Version: 1.1
Name: ncmbot
Version: 0.1.6
Summary: Awesome Python Library, that's NeteaseCloudMusic`s Bot.
Home-page: https://github.com/xiyoumc/ncmbot
Author: XiyouMc
Author-email: xiyoumc.dev@gmail.com
License: ISC
Platform: UNKNOWN
Classifier: Intended Audience :: Developers
Classifier: License :: OSI Approved :: ISC License (ISCL)
Classifier: Programming Language :: Python
Classifier: Programming Language :: Python :: 2.6
Classifier: Programming Language :: Python :: 2.7
